[{"name": "\u5e74\u8f7b\u82d7\u6761\u7559\u5b66\u751f\u5927\u6218\u767d\u4eba\u7c97\u5927\u6d0b\u9e21\u5df4 \u88ab\u5e72\u7684\u5c0f\u903c\u5916\u7ffb \u9ad8\u6f6e\u51e0\u6b21 \u723d\u6b7b\u4e86", "size": 126235776, "link": "https://streamtape.com/e/e3G6d1Q9JKsYvaR", "created_at": "2022\u5e7405\u670801\u65e5 19:57:49", "downloads": 0, "linkid": "e3G6d1Q9JKsYvaR", "convert": "converted", "achorname": "\u4e38\u5b50\u5466", "subscribe": "0\u4f4d\u8ba2\u9605\u8005", "avatar-img": "https://huyaimg.msstatic.com/avatar/1022/07/ec5fef7c7662720286fbbb12395390_180_135.jpg?1628178596?458732", "folderName": "\u5e74\u8f7b\u82d7\u6761\u7559\u5b66\u751f\u5927\u6218\u767d\u4eba\u7c97\u5927\u6d0b\u9e21\u5df4 \u88ab\u5e72\u7684\u5c0f\u903c\u5916\u7ffb \u9ad8\u6f6e\u51e0\u6b21 \u723d\u6b7b\u4e86", "thumbUrl": "https://thumb.tapecontent.net/thumb/e3G6d1Q9JKsYvaR/VY4Wbmxw1Ztx7Y.jpg"}, {"name": "\u9ad8\u989c\u503c\u6deb\u8361\u98ce\u9a9a\u773c\u955c\u59b9\u5b50\u5927\u6218\u7c97\u5927\u9e21\u5df4 \u88ab\u63d2\u5230\u76f4\u7ffb\u767d\u773c \u9ad8\u6f6e\u597d\u51e0\u6b21", "size": 58921903, "link": "https://streamtape.com/e/oellZeGJdKuJ0ok", "created_at": "2022\u5e7405\u670801\u65e5 10:20:26", "downloads": 0, "linkid": "oellZeGJdKuJ0ok", "convert": "converted", "achorname": "\u4e38\u5b50\u5466", "subscribe": "0\u4f4d\u8ba2\u9605\u8005", "avatar-img": "https://huyaimg.msstatic.com/avatar/1022/07/ec5fef7c7662720286fbbb12395390_180_135.jpg?1628178596?458722", "folderName": "\u9ad8\u989c\u503c\u6deb\u8361\u98ce\u9a9a\u773c\u955c\u59b9\u5b50\u5927\u6218\u7c97\u5927\u9e21\u5df4 \u88ab\u63d2\u5230\u76f4\u7ffb\u767d\u773c \u9ad8\u6f6e\u597d\u51e0\u6b21", "thumbUrl": "https://thumb.tapecontent.net/thumb/oellZeGJdKuJ0ok/PjbeGaGB2wC02vp.jpg"}, {"name": "\u534e\u88d4\u6e05\u7eaf\u7559\u5b66\u751f\u88ab\u8001\u5916\u7537\u53cb\u5927\u6d0b\u5c4c\u72c2\u63d2\u731b\u64cd \u6781\u54c1\u5b8c\u7f8e\u8eab\u6750\u8bf1\u4eba\u7684\u5976\u5b50\u80a5\u7f8e\u591a\u6c41\u7684\u9c8d\u9c7c\uff5e2", "size": 122700520, "link": "https://streamtape.com/e/9XRWOwgaMVtazvB", "created_at": "2022\u5e7404\u670829\u65e5 05:59:12", "downloads": 0, "linkid": "9XRWOwgaMVtazvB", "convert": "converted", "achorname": "\u4e38\u5b50\u5466", "subscribe": "0\u4f4d\u8ba2\u9605\u8005", "avatar-img": "https://huyaimg.msstatic.com/avatar/1022/07/ec5fef7c7662720286fbbb12395390_180_135.jpg?1628178596?458670", "folderName": "\u534e\u88d4\u6e05\u7eaf\u7559\u5b66\u751f\u88ab\u8001\u5916\u7537\u53cb\u5927\u6d0b\u5c4c\u72c2\u63d2\u731b\u64cd \u6781\u54c1\u5b8c\u7f8e\u8eab\u6750\u8bf1\u4eba\u7684\u5976\u5b50\u80a5\u7f8e\u591a\u6c41\u7684\u9c8d\u9c7c\uff5e2", "thumbUrl": "https://thumb.tapecontent.net/thumb/9XRWOwgaMVtazvB/z7GBebov14TYZ3O.jpg"}, {"name": "3\u4e2a\u767d\u4eba\u5973\u795e\u6392\u961f\u7b49\u7740\u4f60\u64cd\uff0c\u8001\u54e5\u725b\u903c\u554a\uff0c\u8981\u6362\u6210\u522b\u4eba\u65e9\u5c31\u7cbe\u5c3d\u4eba\u4ea1\u4e86", "size": 127532008, "link": "https://streamtape.com/e/oZmg2je2b0FJ2Aj", "created_at": "2022\u5e7405\u670801\u65e5 08:05:04", "downloads": 0, "linkid": "oZmg2je2b0FJ2Aj", "convert": "converted", "achorname": "\u4e38\u5b50\u5466", "subscribe": "0\u4f4d\u8ba2\u9605\u8005", "avatar-img": "https://huyaimg.msstatic.com/avatar/1022/07/ec5fef7c7662720286fbbb12395390_180_135.jpg?1628178596?458720", "folderName": "3\u4e2a\u767d\u4eba\u5973\u795e\u6392\u961f\u7b49\u7740\u4f60\u64cd\uff0c\u8001\u54e5\u725b\u903c\u554a\uff0c\u8981\u6362\u6210\u522b\u4eba\u65e9\u5c31\u7cbe\u5c3d\u4eba\u4ea1\u4e86", "thumbUrl": "https://thumb.tapecontent.net/thumb/oZmg2je2b0FJ2Aj/pbXOJZAXyAUr8kA.jpg"}, {"name": "\u8fd9\u5c11\u5987\u5f97\u6709\u591a\u9965\u6e34 \u5c04\u4e86\u51e0\u6b21\u4e86\u90fd\u5feb\u6ca1\u8d27\u4e86 \u8fd8\u5728\u53eb\u522b\u55b7\u7ee7\u7eed\u641e\u6211 \u7cbe\u5c3d\u4eba\u4ea1\u554a \u9e21\u5df4\u548b\u4e0d\u4f1a\u8f6f\u5462", "size": 5828758, "link": "https://streamtape.com/e/xOVbloBMDPSkLl3", "created_at": "2022\u5e7405\u670804\u65e5 13:00:17", "downloads": 0, "linkid": "xOVbloBMDPSkLl3", "convert": "converted", "achorname": "\u4e38\u5b50\u5466", "subscribe": "130.3\u4e07\u4f4d\u8ba2\u9605\u8005", "avatar-img": "https://huyaimg.msstatic.com/avatar/1022/07/ec5fef7c7662720286fbbb12395390_180_135.jpg?1628178596?458797", "folderName": "\u8fd9\u5c11\u5987\u5f97\u6709\u591a\u9965\u6e34 \u5c04\u4e86\u51e0\u6b21\u4e86\u90fd\u5feb\u6ca1\u8d27\u4e86 \u8fd8\u5728\u53eb\u522b\u55b7\u7ee7\u7eed\u641e\u6211 \u7cbe\u5c3d\u4eba\u4ea1\u554a \u9e21\u5df4\u548b\u4e0d\u4f1a\u8f6f\u5462", "thumbUrl": "https://thumb.tapecontent.net/thumb/xOVbloBMDPSkLl3/APMRjrWYPOIXOMY.jpg"}, {"name": "wushirenfeijzj - \u4e3b\u52a8\u7ea6\u6211\u597d\u51e0\u6b21\u7684\u5927\u5976\u5b50\u7f8e\u5c11\u5987 \u9ad8\u6e05\u5b8c\u7f8e\u9732\u8138\u539f\u6863", "size": 133746488, "link": "https://streamtape.com/e/1P1q6GgBVkUrp6", "created_at": "2022\u5e7404\u670830\u65e5 19:44:10", "downloads": 0, "linkid": "1P1q6GgBVkUrp6", "convert": "converted", "achorname": "\u4e38\u5b50\u5466", "subscribe": "0\u4f4d\u8ba2\u9605\u8005", "avatar-img": "https://huyaimg.msstatic.com/avatar/1022/07/ec5fef7c7662720286fbbb12395390_180_135.jpg?1628178596?458708", "folderName": "wushirenfeijzj - \u4e3b\u52a8\u7ea6\u6211\u597d\u51e0\u6b21\u7684\u5927\u5976\u5b50\u7f8e\u5c11\u5987 \u9ad8\u6e05\u5b8c\u7f8e\u9732\u8138\u539f\u6863", "thumbUrl": "https://thumb.tapecontent.net/thumb/1P1q6GgBVkUrp6/eogDgABArJiYBLq.jpg"}, {"name": "\u706b\u8fa3\u5927\u5976\u6b63\u59b9\u8fdc\u8d74\u7f8e\u56fd\u62cd\u9ec4\u7247 \u5929\u5929\u88ab\u5404\u79cd\u7c97\u5927\u6d0b\u9e21\u5df4\u5185\u5c04 \u9ad8\u6e05\u7cbe\u5f69\u63a8\u8350", "size": 46955363, "link": "https://streamtape.com/e/wJJ446em0zIJR3q", "created_at": "2022\u5e7404\u670830\u65e5 20:36:30", "downloads": 0, "linkid": "wJJ446em0zIJR3q", "convert": "converted", "achorname": "\u4e38\u5b50\u5466", "subscribe": "0\u4f4d\u8ba2\u9605\u8005", "avatar-img": "https://huyaimg.msstatic.com/avatar/1022/07/ec5fef7c7662720286fbbb12395390_180_135.jpg?1628178596?458708", "folderName": "\u706b\u8fa3\u5927\u5976\u6b63\u59b9\u8fdc\u8d74\u7f8e\u56fd\u62cd\u9ec4\u7247 \u5929\u5929\u88ab\u5404\u79cd\u7c97\u5927\u6d0b\u9e21\u5df4\u5185\u5c04 \u9ad8\u6e05\u7cbe\u5f69\u63a8\u8350", "thumbUrl": "https://thumb.tapecontent.net/thumb/wJJ446em0zIJR3q/Jkgyg10qaKtjzZj.jpg"}, {"name": "\u7ea6\u556a\u80a4\u767d\u8c8c\u7f8e\u4fcf\u4f73\u4eba \u6d6a\u52b2\u5341\u8db3 \u64cd\u8d77\u6765\u7279\u5e26\u52b2 \u4e00\u822c\u731b\u4eba\u8fd8\u771f\u64cd\u4e0d\u52a8\u8fd9\u6837\u6781\u54c1\u5927\u6d0b\u9a6c", "size": 9820683, "link": "https://streamtape.com/e/1dxRQ8kj32ueqvX", "created_at": "2022\u5e7404\u670822\u65e5 15:25:36", "downloads": 0, "linkid": "1dxRQ8kj32ueqvX", "convert": "converted", "achorname": "\u4e38\u5b50\u5466", "subscribe": "0\u4f4d\u8ba2\u9605\u8005", "avatar-img": "https://huyaimg.msstatic.com/avatar/1022/07/ec5fef7c7662720286fbbb12395390_180_135.jpg?1628178596?458648", "folderName": "\u7ea6\u556a\u80a4\u767d\u8c8c\u7f8e\u4fcf\u4f73\u4eba \u6d6a\u52b2\u5341\u8db3 \u64cd\u8d77\u6765\u7279\u5e26\u52b2 \u4e00\u822c\u731b\u4eba\u8fd8\u771f\u64cd\u4e0d\u52a8\u8fd9\u6837\u6781\u54c1\u5927\u6d0b\u9a6c", "thumbUrl": "https://thumb.tapecontent.net/thumb/1dxRQ8kj32ueqvX/yDaWjG4wj6i16L4.jpg"}, {"name": "\u5927\u795e\u9ad8\u989c\u503c\u6821\u82b1\u5973\u53cb\u7ea6\u70ae\uff0c\u8214\u6a31\u5507\u723d\u5f97\u5973\u53cb\u72c2\u558a\u4e0d\u884c\u4e0d\u884c\u5566\uff0c\u8fd9\u5c31\u9ad8\u6f6e\u4e86\uff0c\u518d\u63d2\u5c04\u4e24\u70ae\uff0c\u723d\u6b7b\u8fd9\u5973\u7684\uff01", "size": 83985597, "link": "https://streamtape.com/e/1BBGpy4mPJCeYZa", "created_at": "2022\u5e7405\u670801\u65e5 11:13:12", "downloads": 0, "linkid": "1BBGpy4mPJCeYZa", "convert": "converted", "achorname": "\u4e38\u5b50\u5466", "subscribe": "0\u4f4d\u8ba2\u9605\u8005", "avatar-img": "https://huyaimg.msstatic.com/avatar/1022/07/ec5fef7c7662720286fbbb12395390_180_135.jpg?1628178596?458723", "folderName": "\u5927\u795e\u9ad8\u989c\u503c\u6821\u82b1\u5973\u53cb\u7ea6\u70ae\uff0c\u8214\u6a31\u5507\u723d\u5f97\u5973\u53cb\u72c2\u558a\u4e0d\u884c\u4e0d\u884c\u5566\uff0c\u8fd9\u5c31\u9ad8\u6f6e\u4e86\uff0c\u518d\u63d2\u5c04\u4e24\u70ae\uff0c\u723d\u6b7b\u8fd9\u5973\u7684\uff01", "thumbUrl": "https://thumb.tapecontent.net/thumb/1BBGpy4mPJCeYZa/xmwry4dOx3uk3Xw.jpg"}, {"name": "\u72fc\u54e5\u96c7\u4f63\u9ed1\u4eba\u7559\u5b66\u751f\u9152\u5e97\u5ad6\u5993\u5077\u62cd\u521a\u4e0b\u6d77\u7684\u5e74\u8f7b\u7f8e\u5c11\u5987\u6027\u611f\u62a4\u58eb\u88c5\u548c\u5c0f\u9ed1\u72fc\u54e53P\u5927\u6218", "size": 144670187, "link": "https://streamtape.com/e/GvpBmd2KYJcdLo", "created_at": "2022\u5e7404\u670823\u65e5 21:00:18", "downloads": 0, "linkid": "GvpBmd2KYJcdLo", "convert": "converted", "achorname": "\u4e38\u5b50\u5466", "subscribe": "0\u4f4d\u8ba2\u9605\u8005", "avatar-img": "https://huyaimg.msstatic.com/avatar/1022/07/ec5fef7c7662720286fbbb12395390_180_135.jpg?1628178596?458648", "folderName": "\u72fc\u54e5\u96c7\u4f63\u9ed1\u4eba\u7559\u5b66\u751f\u9152\u5e97\u5ad6\u5993\u5077\u62cd\u521a\u4e0b\u6d77\u7684\u5e74\u8f7b\u7f8e\u5c11\u5987\u6027\u611f\u62a4\u58eb\u88c5\u548c\u5c0f\u9ed1\u72fc\u54e53P\u5927\u6218", "thumbUrl": "https://thumb.tapecontent.net/thumb/GvpBmd2KYJcdLo/q3vKG7Ap4Gfzzp2.jpg"}, {"name": "\u517b\u751f\u6309\u6469\u4f1a\u6240\u82d7\u6761\u7f8e\u817f\u6280\u5e08\u4e00\u6761\u9f99\u9500\u9b42\u670d\u52a1\u5168\u8eab\u6e38\u8d70\u6bd2\u9f99\u9876\u809b\u723d\u6b7b\u4eba\u4e8c\u6307\u7985\u4f7f\u52b2\u62a0\u5979\u6fc0\u60c5\u53e3\u7206\u723d\u5b8c\u518d\u8ba9\u7f8e\u5973\u91c7\u4e2a\u8033", "size": 331428816, "link": "https://streamtape.com/e/g113OkMm0lixK8", "created_at": "2022\u5e7405\u670804\u65e5 05:15:31", "downloads": 0, "linkid": "g113OkMm0lixK8", "convert": "converted", "achorname": "\u4e38\u5b50\u5466", "subscribe": "0\u4f4d\u8ba2\u9605\u8005", "avatar-img": "https://huyaimg.msstatic.com/avatar/1022/07/ec5fef7c7662720286fbbb12395390_180_135.jpg?1628178596?458789", "folderName": "\u517b\u751f\u6309\u6469\u4f1a\u6240\u82d7\u6761\u7f8e\u817f\u6280\u5e08\u4e00\u6761\u9f99\u9500\u9b42\u670d\u52a1\u5168\u8eab\u6e38\u8d70\u6bd2\u9f99\u9876\u809b\u723d\u6b7b\u4eba\u4e8c\u6307\u7985\u4f7f\u52b2\u62a0\u5979\u6fc0\u60c5\u53e3\u7206\u723d\u5b8c\u518d\u8ba9\u7f8e\u5973\u91c7\u4e2a\u8033", "thumbUrl": "https://thumb.tapecontent.net/thumb/g113OkMm0lixK8/VV6KJoMxw3TKD4J.jpg"}, {"name": "\u82d7\u6761\u7f8e\u5c11\u5987\u7ea6\u4e86\u4e2a\u5e74\u8f7b\u5c0f\u4f19\u9152\u5e97\u556a\u556a", "size": 173924447, "link": "https://streamtape.com/e/Be6Wa2Vp0PTy1a3", "created_at": "2022\u5e7404\u670822\u65e5 14:42:31", "downloads": 0, "linkid": "Be6Wa2Vp0PTy1a3", "convert": "converted", "achorname": "\u4e38\u5b50\u5466", "subscribe": "0\u4f4d\u8ba2\u9605\u8005", "avatar-img": "https://huyaimg.msstatic.com/avatar/1022/07/ec5fef7c7662720286fbbb12395390_180_135.jpg?1628178596?458648", "folderName": "\u82d7\u6761\u7f8e\u5c11\u5987\u7ea6\u4e86\u4e2a\u5e74\u8f7b\u5c0f\u4f19\u9152\u5e97\u556a\u556a", "thumbUrl": "https://thumb.tapecontent.net/thumb/Be6Wa2Vp0PTy1a3/DlvXVV6YbZUkplL.jpg"}, {"name": "\u5973\u795e\u4e0b\u6d77\u3010\u4e1d\u889c\u5996\u59ec\u5450\u3011\u989c\u503c\u8eab\u6750\u90fd\u4e00\u6d41\uff0c\u4e1d\u889c\u63a7\uff0c\u5927\u9ed1\u725b\u8df3\u86cb\u5f04\u5f97\u9ad8\u6f6e\u8fde\u8fde\uff0c\u2018\u554a\u554a\u554a \u723d\u6b7b\u6211\u5566\uff0c\u5168\u662f\u6deb\u6c34\u2019\uff01", "size": 254333268, "link": "https://streamtape.com/e/7qD0BPqOZxSA7rW", "created_at": "2022\u5e7405\u670804\u65e5 18:43:27", "downloads": 0, "linkid": "7qD0BPqOZxSA7rW", "convert": "converted", "achorname": "\u4e38\u5b50\u5466", "subscribe": "0\u4f4d\u8ba2\u9605\u8005", "avatar-img": "https://huyaimg.msstatic.com/avatar/1022/07/ec5fef7c7662720286fbbb12395390_180_135.jpg?1628178596?458803", "folderName": "\u5973\u795e\u4e0b\u6d77\u3010\u4e1d\u889c\u5996\u59ec\u5450\u3011\u989c\u503c\u8eab\u6750\u90fd\u4e00\u6d41\uff0c\u4e1d\u889c\u63a7\uff0c\u5927\u9ed1\u725b\u8df3\u86cb\u5f04\u5f97\u9ad8\u6f6e\u8fde\u8fde\uff0c\u2018\u554a\u554a\u554a \u723d\u6b7b\u6211\u5566\uff0c\u5168\u662f\u6deb\u6c34\u2019\uff01", "thumbUrl": "https://thumb.tapecontent.net/thumb/7qD0BPqOZxSA7rW/zp6M8wXqpoHoRq.jpg"}, {"name": "\u571f\u8c6a\u54e5\u4e13\u4e1a\u8349\u8001\u59164P\u6b27\u7f8e\u5927\u6d0b\u9a6c\uff0c\u4e09\u4e2a\u9a9a\u903c\u8f6e\u6d41\u7ed9\u5927\u54e5\u8214\u5927\u9e21\u5df4\uff0c\u8ba9\u5927\u54e5\u5404\u79cd\u73a9\u5f04\u6253\u5976\u70ae\u76f4\u63a5\u6345\u5230\u5634\uff0c\u8f6e\u8349\u4e09\u59732", "size": 238107032, "link": "https://streamtape.com/e/XJaK6L81OaFDjXA", "created_at": "2022\u5e7404\u670829\u65e5 12:15:12", "downloads": 0, "linkid": "XJaK6L81OaFDjXA", "convert": "converted", "achorname": "\u4e38\u5b50\u5466", "subscribe": "0\u4f4d\u8ba2\u9605\u8005", "avatar-img": "https://huyaimg.msstatic.com/avatar/1022/07/ec5fef7c7662720286fbbb12395390_180_135.jpg?1628178596?458676", "folderName": "\u571f\u8c6a\u54e5\u4e13\u4e1a\u8349\u8001\u59164P\u6b27\u7f8e\u5927\u6d0b\u9a6c\uff0c\u4e09\u4e2a\u9a9a\u903c\u8f6e\u6d41\u7ed9\u5927\u54e5\u8214\u5927\u9e21\u5df4\uff0c\u8ba9\u5927\u54e5\u5404\u79cd\u73a9\u5f04\u6253\u5976\u70ae\u76f4\u63a5\u6345\u5230\u5634\uff0c\u8f6e\u8349\u4e09\u59732", "thumbUrl": "https://thumb.tapecontent.net/thumb/XJaK6L81OaFDjXA/gvxbeRdp34Cqw24.jpg"}, {"name": "\u989c\u503c\u9ad8\u82d7\u6761\u9a9a\u5987\u6d74\u7f38\u5927\u6218", "size": 105545987, "link": "https://streamtape.com/e/DqmrbQrDq7Fk7mm", "created_at": "2022\u5e7404\u670825\u65e5 07:44:44", "downloads": 0, "linkid": "DqmrbQrDq7Fk7mm", "convert": "converted", "achorname": "\u4e38\u5b50\u5466", "subscribe": "0\u4f4d\u8ba2\u9605\u8005", "avatar-img": "https://huyaimg.msstatic.com/avatar/1022/07/ec5fef7c7662720286fbbb12395390_180_135.jpg?1628178596?458648", "folderName": "\u989c\u503c\u9ad8\u82d7\u6761\u9a9a\u5987\u6d74\u7f38\u5927\u6218", "thumbUrl": "https://thumb.tapecontent.net/thumb/DqmrbQrDq7Fk7mm/qrG61PmkzjCzryR.jpg"}, {"name": "\u9ad8\u4ef7\u7f51\u7ea6\u4e24\u4e2a\u841d\u8389\u578b\u517c\u804c\u5ae9\u59b9\u53cc\u98de\uff0c\u725b\u4ed4\u88d9\u6781\u54c1\u5c0f\u59d0\u59d0\uff0c\u4e00\u6d41\u989c\u503c\u4fee\u957f\u7f8e\u817f\uff0c\u53cc\u5973\u4e00\u8d77\u670d\u52a1\u723d\u6b7b\uff0c\u9a91\u4e58\u540e\u5165\u8f6e\u6d41\u64cd", "size": 239918757, "link": "https://streamtape.com/e/BzwMa29R0PFM3w", "created_at": "2022\u5e7404\u670822\u65e5 20:34:13", "downloads": 0, "linkid": "BzwMa29R0PFM3w", "convert": "converted", "achorname": "\u4e38\u5b50\u5466", "subscribe": "0\u4f4d\u8ba2\u9605\u8005", "avatar-img": "https://huyaimg.msstatic.com/avatar/1022/07/ec5fef7c7662720286fbbb12395390_180_135.jpg?1628178596?458648", "folderName": "\u9ad8\u4ef7\u7f51\u7ea6\u4e24\u4e2a\u841d\u8389\u578b\u517c\u804c\u5ae9\u59b9\u53cc\u98de\uff0c\u725b\u4ed4\u88d9\u6781\u54c1\u5c0f\u59d0\u59d0\uff0c\u4e00\u6d41\u989c\u503c\u4fee\u957f\u7f8e\u817f\uff0c\u53cc\u5973\u4e00\u8d77\u670d\u52a1\u723d\u6b7b\uff0c\u9a91\u4e58\u540e\u5165\u8f6e\u6d41\u64cd", "thumbUrl": "https://thumb.tapecontent.net/thumb/BzwMa29R0PFM3w/vYKXzRljPyT41da.jpg"}, {"name": "\u5bbe\u99863P\u65e0\u6bdb\u7f8e\u5c11\u5987 \u9a9a\u903c\u4e0d\u884c\u4e86 \u9ad8\u6f6e\u4e86 \u5230\u5e95\u4e86\u5230\u5e95\u4e86 \u8fd9\u5931\u58f0\u5927\u53eb \u5413\u7684\u5927\u54e5\u51e0\u6b21\u62ff\u624b\u6342\u5979\u5634", "size": 7503615, "link": "https://streamtape.com/e/rdDgAW8XzLfbZLR", "created_at": "2022\u5e7405\u670802\u65e5 02:57:18", "downloads": 0, "linkid": "rdDgAW8XzLfbZLR", "convert": "converted", "achorname": "\u4e38\u5b50\u5466", "subscribe": "0\u4f4d\u8ba2\u9605\u8005", "avatar-img": "https://huyaimg.msstatic.com/avatar/1022/07/ec5fef7c7662720286fbbb12395390_180_135.jpg?1628178596?458738", "folderName": "\u5bbe\u99863P\u65e0\u6bdb\u7f8e\u5c11\u5987 \u9a9a\u903c\u4e0d\u884c\u4e86 \u9ad8\u6f6e\u4e86 \u5230\u5e95\u4e86\u5230\u5e95\u4e86 \u8fd9\u5931\u58f0\u5927\u53eb \u5413\u7684\u5927\u54e5\u51e0\u6b21\u62ff\u624b\u6342\u5979\u5634", "thumbUrl": "https://thumb.tapecontent.net/thumb/rdDgAW8XzLfbZLR/zD4AkDk01LSYA2A.jpg"}, {"name": "\u9152\u5e97\u64cd\u4e00\u7c73\u4e03\u591a\u7684\u9ad8\u6311\u6e05\u79c0\u7f8e\u5973\uff0c\u8089\u4f53\u767d\u767d\u5ae9\u5ae9\u7684\u5976\u5b50\u8f6f\u5927\u817f\u4e5f\u4e0d\u9519\u770b\u7684\u80c3\u53e3\u5927\u5f00\u63d2\u5165\u731b\u641e\u556a\u556a\u597d\u51e0\u6b21", "size": 97199672, "link": "https://streamtape.com/e/8KgMlll6WyUoRol", "created_at": "2022\u5e7404\u670823\u65e5 19:53:38", "downloads": 0, "linkid": "8KgMlll6WyUoRol", "convert": "converted", "achorname": "\u4e38\u5b50\u5466", "subscribe": "0\u4f4d\u8ba2\u9605\u8005", "avatar-img": "https://huyaimg.msstatic.com/avatar/1022/07/ec5fef7c7662720286fbbb12395390_180_135.jpg?1628178596?458648", "folderName": "\u9152\u5e97\u64cd\u4e00\u7c73\u4e03\u591a\u7684\u9ad8\u6311\u6e05\u79c0\u7f8e\u5973\uff0c\u8089\u4f53\u767d\u767d\u5ae9\u5ae9\u7684\u5976\u5b50\u8f6f\u5927\u817f\u4e5f\u4e0d\u9519\u770b\u7684\u80c3\u53e3\u5927\u5f00\u63d2\u5165\u731b\u641e\u556a\u556a\u597d\u51e0\u6b21", "thumbUrl": "https://thumb.tapecontent.net/thumb/8KgMlll6WyUoRol/PkqG0mBOZXT0qkj.jpg"}, {"name": "\u9ad8\u989c\u503c\u6e05\u7eaf\u5927\u5b66\u7559\u5b66\u751f\u4f18\u7c73\u548c\u95fa\u871c\u4e00\u8d77\u4f3a\u5019\u7537\u53cb \u53e3\u6d3b\u52b2\u9053\u6709\u5438\u529b\u5f88\u6709\u5f53AV\u5973\u4f18\u7684\u6f5c\u8d28 \u65e0\u5957\u540e\u5165\u6d6a\u53eb", "size": 95696340, "link": "https://streamtape.com/e/GbowK66ee1H1kWl", "created_at": "2022\u5e7404\u670823\u65e5 20:37:05", "downloads": 0, "linkid": "GbowK66ee1H1kWl", "convert": "converted", "achorname": "\u4e38\u5b50\u5466", "subscribe": "0\u4f4d\u8ba2\u9605\u8005", "avatar-img": "https://huyaimg.msstatic.com/avatar/1022/07/ec5fef7c7662720286fbbb12395390_180_135.jpg?1628178596?458648", "folderName": "\u9ad8\u989c\u503c\u6e05\u7eaf\u5927\u5b66\u7559\u5b66\u751f\u4f18\u7c73\u548c\u95fa\u871c\u4e00\u8d77\u4f3a\u5019\u7537\u53cb \u53e3\u6d3b\u52b2\u9053\u6709\u5438\u529b\u5f88\u6709\u5f53AV\u5973\u4f18\u7684\u6f5c\u8d28 \u65e0\u5957\u540e\u5165\u6d6a\u53eb", "thumbUrl": "https://thumb.tapecontent.net/thumb/GbowK66ee1H1kWl/lkrVYKzg9lsZPe.jpg"}, {"name": "\u64b8\u70b9\u6781\u9ad8 \u8d85\u7ea7\u53ef\u7231\u7684\u767d\u864e\u841d\u8389\uff0c\u6709\u7740\u53f2\u4e0a\u300e\u6700\u6781\u54c1\u7684\u7c89\u7a74\u4e4b\u4e00\u300f\uff0c\u88ab\u5927\u53d4\u66b4\u529b\u64cd \u8fde\u7eed\u9ad8\u6f6e\u53d1\u6296\u4e86\u597d\u51e0\u6b21\uff0c\u9178\u723d\u7684\u9762\u90e8\u8868\u60c5\u662f\u4e00\u5927\u4eae\u70b9", "size": 68620050, "link": "https://streamtape.com/e/xy4DZ8JpA9FkPBX", "created_at": "2022\u5e7405\u670803\u65e5 23:16:27", "downloads": 0, "linkid": "xy4DZ8JpA9FkPBX", "convert": "converted", "achorname": "\u4e38\u5b50\u5466", "subscribe": "0\u4f4d\u8ba2\u9605\u8005", "avatar-img": "https://huyaimg.msstatic.com/avatar/1022/07/ec5fef7c7662720286fbbb12395390_180_135.jpg?1628178596?458783", "folderName": "\u64b8\u70b9\u6781\u9ad8 \u8d85\u7ea7\u53ef\u7231\u7684\u767d\u864e\u841d\u8389\uff0c\u6709\u7740\u53f2\u4e0a\u300e\u6700\u6781\u54c1\u7684\u7c89\u7a74\u4e4b\u4e00\u300f\uff0c\u88ab\u5927\u53d4\u66b4\u529b\u64cd \u8fde\u7eed\u9ad8\u6f6e\u53d1\u6296\u4e86\u597d\u51e0\u6b21\uff0c\u9178\u723d\u7684\u9762\u90e8\u8868\u60c5\u662f\u4e00\u5927\u4eae\u70b9", "thumbUrl": "https://thumb.tapecontent.net/thumb/xy4DZ8JpA9FkPBX/YgDKOBdMR8FpyR.jpg"}, {"name": "\u82d7\u6761\u5c0f\u5ae9\u59b9\u5927\u6218\u7c97\u957f\u5c4c \u76f4\u9876\u82b1\u5fc3 \u9ad8\u6f6e\u76f4\u63a5\u5c31\u6765\u4e86", "size": 32713016, "link": "https://streamtape.com/e/V81xbGAXQqukz3", "created_at": "2022\u5e7405\u670802\u65e5 04:41:37", "downloads": 0, "linkid": "V81xbGAXQqukz3", "convert": "converted", "achorname": "\u4e38\u5b50\u5466", "subscribe": "0\u4f4d\u8ba2\u9605\u8005", "avatar-img": "https://huyaimg.msstatic.com/avatar/1022/07/ec5fef7c7662720286fbbb12395390_180_135.jpg?1628178596?458740", "folderName": "\u82d7\u6761\u5c0f\u5ae9\u59b9\u5927\u6218\u7c97\u957f\u5c4c \u76f4\u9876\u82b1\u5fc3 \u9ad8\u6f6e\u76f4\u63a5\u5c31\u6765\u4e86", "thumbUrl": "https://thumb.tapecontent.net/thumb/V81xbGAXQqukz3/RpjyMKaJQaSdveL.jpg"}, {"name": "10858", "size": 502765306, "link": "https://streamtape.com/e/LJ3Aq91eYyTRrM8", "created_at": "2022\u5e7403\u670811\u65e5 22:39:42", "downloads": 0, "linkid": "LJ3Aq91eYyTRrM8", "convert": "converted", "achorname": "\u4e38\u5b50\u5466", "subscribe": "0\u4f4d\u8ba2\u9605\u8005", "avatar-img": "https://huyaimg.msstatic.com/avatar/1022/07/ec5fef7c7662720286fbbb12395390_180_135.jpg?1628178596?458648", "folderName": "\u868a\u9999\u793e\u4e0d\u80fd\u8f93SOD\uff01 \u300a\u82e5\u83dc\u5948\u592e\u300b\u4e00\u5bf9\u4e00\u5e72\u70ae\u723d\u6b7b\u65e0\u7801\u5b8c\u6574\u6d41\u51fa97\u5206\u949f \u903c\u6709\u591f\u9ed1\u90fd\u88ab\u770b\u5149\u3002", "thumbUrl": "https://file.tktube.com/contents/videos_screenshots/10000/10858/336x189/1.jpg"}, {"name": "\u8fde\u4f53\u4e1d\u889c\u5996\u8273\u7684\u6f6e\u5439\u5973\u738b\uff0c\u81ea\u6765\u6c34\u4e00\u822c\u7684\u6f6e\u6c34\u8bf4\u6765\u5c31\u6765\uff0c\u6253\u4e2a\u70ae\u90fd\u80fd\u55b7\u597d\u51e0\u6b21\u6c34\uff0c\u6f6e\u6c34\u56db\u5904\u98de\u6e85\uff0c\u628a\u4e1d\u889c\u548c\u838e\u53d1\u90fd\u641e\u6e7f\u4e86", "size": 152065474, "link": "https://streamtape.com/e/BO0qoj936WhyaGB", "created_at": "2022\u5e7404\u670825\u65e5 14:57:19", "downloads": 0, "linkid": "BO0qoj936WhyaGB", "convert": "converted", "achorname": "\u4e38\u5b50\u5466", "subscribe": "0\u4f4d\u8ba2\u9605\u8005", "avatar-img": "https://huyaimg.msstatic.com/avatar/1022/07/ec5fef7c7662720286fbbb12395390_180_135.jpg?1628178596?458648", "folderName": "\u8fde\u4f53\u4e1d\u889c\u5996\u8273\u7684\u6f6e\u5439\u5973\u738b\uff0c\u81ea\u6765\u6c34\u4e00\u822c\u7684\u6f6e\u6c34\u8bf4\u6765\u5c31\u6765\uff0c\u6253\u4e2a\u70ae\u90fd\u80fd\u55b7\u597d\u51e0\u6b21\u6c34\uff0c\u6f6e\u6c34\u56db\u5904\u98de\u6e85\uff0c\u628a\u4e1d\u889c\u548c\u838e\u53d1\u90fd\u641e\u6e7f\u4e86", "thumbUrl": "https://thumb.tapecontent.net/thumb/BO0qoj936WhyaGB/l4GDeD2Q3Wc7J3Q.jpg"}, {"name": "\u63a2\u82b1\u90ce\u674e\u5bfb\u6b2201-15\u5927\u6218\u5973\u4e3b\u64ad", "size": 567593222, "link": "https://streamtape.com/e/D4JjqK08qaUk7km", "created_at": "2022\u5e7403\u670814\u65e5 15:56:55", "downloads": 0, "linkid": "D4JjqK08qaUk7km", "convert": "converted", "achorname": "\u4e38\u5b50\u5466", "subscribe": "0\u4f4d\u8ba2\u9605\u8005", "avatar-img": "https://huyaimg.msstatic.com/avatar/1022/07/ec5fef7c7662720286fbbb12395390_180_135.jpg?1628178596?458648", "folderName": "\u63a2\u82b1\u90ce\u674e\u5bfb\u6b2201-15\u5927\u6218\u5973\u4e3b\u64ad", "thumbUrl": "https://thumb.tapecontent.net/thumb/D4JjqK08qaUk7km/v918AjMZvvh4Xva.jpg"}, {"name": "\u9ad8\u989c\u503c\u7559\u5b66\u751f\u88ab\u9ed1\u4eba\u6253\u6869\u673a\u8e42\u8e8f \u5404\u79cd\u59ff\u52bf\u64cd\u86cb\u4e0d\u8981\u4e0d\u8981\u7684", "size": 16016325, "link": "https://streamtape.com/e/vxYp0lkrKYF49ow", "created_at": "2022\u5e7405\u670801\u65e5 08:42:07", "downloads": 0, "linkid": "vxYp0lkrKYF49ow", "convert": "converted", "achorname": "\u4e38\u5b50\u5466", "subscribe": "0\u4f4d\u8ba2\u9605\u8005", "avatar-img": "https://huyaimg.msstatic.com/avatar/1022/07/ec5fef7c7662720286fbbb12395390_180_135.jpg?1628178596?458720", "folderName": "\u9ad8\u989c\u503c\u7559\u5b66\u751f\u88ab\u9ed1\u4eba\u6253\u6869\u673a\u8e42\u8e8f \u5404\u79cd\u59ff\u52bf\u64cd\u86cb\u4e0d\u8981\u4e0d\u8981\u7684", "thumbUrl": "https://thumb.tapecontent.net/thumb/vxYp0lkrKYF49ow/qJooARaqZYTzqgm.jpg"}, {"name": "\u4f1f\u54e5\u63a2\u4f1a\u62403.31\u53c8\u5dee\u70b9\u7ffb\u8f66\u5e97\u5185\u989c\u503c\u8eab\u6750\u5934\u724c\u5973\u6280\u5e08\u806a\u660e\u7684\u5f88\u4e24\u6b21\u632a\u52a8\u955c\u5934\u4f1f\u54e5\u53d1\u706b\u53ea\u597d\u5356\u529b\u670d\u52a1\u6e38\u8d70\u6bd2\u9f9969\u4e92\u8214\u723d\u6b7b\u4eba", "size": 201606660, "link": "https://streamtape.com/e/k9zvZR0A4LHOdPx", "created_at": "2022\u5e7405\u670804\u65e5 04:14:22", "downloads": 0, "linkid": "k9zvZR0A4LHOdPx", "convert": "converted", "achorname": "\u4e38\u5b50\u5466", "subscribe": "0\u4f4d\u8ba2\u9605\u8005", "avatar-img": "https://huyaimg.msstatic.com/avatar/1022/07/ec5fef7c7662720286fbbb12395390_180_135.jpg?1628178596?458788", "folderName": "\u4f1f\u54e5\u63a2\u4f1a\u62403.31\u53c8\u5dee\u70b9\u7ffb\u8f66\u5e97\u5185\u989c\u503c\u8eab\u6750\u5934\u724c\u5973\u6280\u5e08\u806a\u660e\u7684\u5f88\u4e24\u6b21\u632a\u52a8\u955c\u5934\u4f1f\u54e5\u53d1\u706b\u53ea\u597d\u5356\u529b\u670d\u52a1\u6e38\u8d70\u6bd2\u9f9969\u4e92\u8214\u723d\u6b7b\u4eba", "thumbUrl": "https://thumb.tapecontent.net/thumb/k9zvZR0A4LHOdPx/kpzv1Z72m6cOGd7.jpg"}, {"name": "dasd-696_1", "size": 1106773640, "link": "https://streamtape.com/e/41BVLmjMx8FKwOe", "created_at": "2022\u5e7403\u670828\u65e5 03:29:19", "downloads": 0, "linkid": "41BVLmjMx8FKwOe", "convert": "converted", "achorname": "\u4e38\u5b50\u5466", "subscribe": "0\u4f4d\u8ba2\u9605\u8005", "avatar-img": "https://huyaimg.msstatic.com/avatar/1022/07/ec5fef7c7662720286fbbb12395390_180_135.jpg?1628178596?458648", "folderName": "DASD-696 \u628a\u7f8e\u5973\u5927\u6d0b\u99ac\u82f1\u8a9e\u6559\u5e2b\u59d0\u59b9\u50ac\u7720\u6d17\u8166\u8b8a\u6210\u8b8a\u6210\u6e34\u6c42\u6211\u8089\u68d2\u7684\u6deb\u8569\u5973\u4eba \u897f\u7530\u5361\u8389\u5a1c June Lovejoy", "thumbUrl": "https://assets-cdn.jable.tv/contents/videos_screenshots/9000/9268/320x180/1.jpg"}, {"name": "\u3010\u6781\u54c1\u5916\u56f4\u63a2\u82b1\u3011\u65b0\u664b\u63a2\u82b1\u5927\u6218\u82d7\u6761\u517c\u804c\u5b66\u751f\u59b9\uff0c\u80c6\u5b50\u5927\u76f4\u63a5\u5077\u62cd\u6d17\u6fa1\uff0c\u4e56\u5de7\u542c\u8bdd\u8fd1\u666f\u556a\u556a", "size": 177513031, "link": "https://streamtape.com/e/74GW4oj0eQtAOj9", "created_at": "2022\u5e7404\u670830\u65e5 04:10:46", "downloads": 0, "linkid": "74GW4oj0eQtAOj9", "convert": "converted", "achorname": "\u4e38\u5b50\u5466", "subscribe": "0\u4f4d\u8ba2\u9605\u8005", "avatar-img": "https://huyaimg.msstatic.com/avatar/1022/07/ec5fef7c7662720286fbbb12395390_180_135.jpg?1628178596?458692", "folderName": "\u3010\u6781\u54c1\u5916\u56f4\u63a2\u82b1\u3011\u65b0\u664b\u63a2\u82b1\u5927\u6218\u82d7\u6761\u517c\u804c\u5b66\u751f\u59b9\uff0c\u80c6\u5b50\u5927\u76f4\u63a5\u5077\u62cd\u6d17\u6fa1\uff0c\u4e56\u5de7\u542c\u8bdd\u8fd1\u666f\u556a\u556a", "thumbUrl": "https://thumb.tapecontent.net/thumb/74GW4oj0eQtAOj9/p8Zbv7J7mmuxpM.jpg"}, {"name": "\u571f\u8c6a\u9ad8\u7ea7\u9152\u5e97\u5927\u6218\u5927\u5976\u5b50\u7f8e\u5973\u6a21\u7279\u9732\u8138\u5b8c\u6574\u7248", "size": 93592899, "link": "https://streamtape.com/e/XYeexGzdZKhAl0", "created_at": "2022\u5e7404\u670830\u65e5 13:16:11", "downloads": 0, "linkid": "XYeexGzdZKhAl0", "convert": "converted", "achorname": "\u4e38\u5b50\u5466", "subscribe": "130.3\u4e07\u4f4d\u8ba2\u9605\u8005", "avatar-img": "https://huyaimg.msstatic.com/avatar/1022/07/ec5fef7c7662720286fbbb12395390_180_135.jpg?1628178596?458701", "folderName": "\u571f\u8c6a\u9ad8\u7ea7\u9152\u5e97\u5927\u6218\u5927\u5976\u5b50\u7f8e\u5973\u6a21\u7279\u9732\u8138\u5b8c\u6574\u7248", "thumbUrl": "https://thumb.tapecontent.net/thumb/XYeexGzdZKhAl0/klLrpOvz3Wieel.jpg"}, {"name": "\u6deb\u8361\u7559\u5b66\u751f\u300eMaominvshen\u300f\u4e0e\u5916\u56fd\u7537\u53cb\u7684\u6fc0\u60c5\u6027\u7231\u751f\u6d3b\u7cfb\u5217-\u6346\u7ed1\u675f\u7f1a\u540a\u5728\u95e8\u6846\u4e0a\u73a9\u5f04\u6f6e\u5439\u540e\u518d\u63d2\u5c0f\u9a9a\u903c", "size": 147910543, "link": "https://streamtape.com/e/1jPX0RPvMeiegMp", "created_at": "2022\u5e7404\u670830\u65e5 10:42:08", "downloads": 0, "linkid": "1jPX0RPvMeiegMp", "convert": "converted", "achorname": "\u4e38\u5b50\u5466", "subscribe": "0\u4f4d\u8ba2\u9605\u8005", "avatar-img": "https://huyaimg.msstatic.com/avatar/1022/07/ec5fef7c7662720286fbbb12395390_180_135.jpg?1628178596?458698", "folderName": "\u6deb\u8361\u7559\u5b66\u751f\u300eMaominvshen\u300f\u4e0e\u5916\u56fd\u7537\u53cb\u7684\u6fc0\u60c5\u6027\u7231\u751f\u6d3b\u7cfb\u5217-\u6346\u7ed1\u675f\u7f1a\u540a\u5728\u95e8\u6846\u4e0a\u73a9\u5f04\u6f6e\u5439\u540e\u518d\u63d2\u5c0f\u9a9a\u903c", "thumbUrl": "https://thumb.tapecontent.net/thumb/1jPX0RPvMeiegMp/qKOaR2geg6hz32z.jpg"}, {"name": "\u4e03\u5929\u9ad8\u7aef\u5916\u56f401-18\u82d7\u6761\u9ad8\u6f6e\u59b9", "size": 331789702, "link": "https://streamtape.com/e/yDWR6GAYv8fm6X", "created_at": "2022\u5e7403\u670814\u65e5 06:52:19", "downloads": 0, "linkid": "yDWR6GAYv8fm6X", "convert": "converted", "achorname": "\u4e38\u5b50\u5466", "subscribe": "0\u4f4d\u8ba2\u9605\u8005", "avatar-img": "https://huyaimg.msstatic.com/avatar/1022/07/ec5fef7c7662720286fbbb12395390_180_135.jpg?1628178596?458648", "folderName": "\u4e03\u5929\u9ad8\u7aef\u5916\u56f401-18\u82d7\u6761\u9ad8\u6f6e\u59b9", "thumbUrl": "https://thumb.tapecontent.net/thumb/yDWR6GAYv8fm6X/okGmwwAJOjcJqdV.jpg"}, {"name": "\u72fc\u54e5\u96c7\u4f63\u9ed1\u4eba\u7559\u5b66\u751f\u9152\u5e97\u5ad6\u5993\u5077\u62cd2000\u5757\u7ea6\u7684\u8eab\u6750\u82d7\u6761\u5e74\u8f7b\u5356\u6deb\u5973\u5e72\u4e00\u534a\u4e0d\u8ba9\u5e72\u4e86\u5c0f\u9ed1\u628a\u72fc\u54e5\u62db\u547c\u6765\u4e86\u5e72\u5b8c\u624d\u8ba9\u8d70", "size": 143859964, "link": "https://streamtape.com/e/GPXy78kGBXs1vAV", "created_at": "2022\u5e7404\u670828\u65e5 07:56:46", "downloads": 0, "linkid": "GPXy78kGBXs1vAV", "convert": "converted", "achorname": "\u4e38\u5b50\u5466", "subscribe": "0\u4f4d\u8ba2\u9605\u8005", "avatar-img": "https://huyaimg.msstatic.com/avatar/1022/07/ec5fef7c7662720286fbbb12395390_180_135.jpg?1628178596?458648", "folderName": "\u72fc\u54e5\u96c7\u4f63\u9ed1\u4eba\u7559\u5b66\u751f\u9152\u5e97\u5ad6\u5993\u5077\u62cd2000\u5757\u7ea6\u7684\u8eab\u6750\u82d7\u6761\u5e74\u8f7b\u5356\u6deb\u5973\u5e72\u4e00\u534a\u4e0d\u8ba9\u5e72\u4e86\u5c0f\u9ed1\u628a\u72fc\u54e5\u62db\u547c\u6765\u4e86\u5e72\u5b8c\u624d\u8ba9\u8d70", "thumbUrl": "https://thumb.tapecontent.net/thumb/GPXy78kGBXs1vAV/4dlv9r9md0iVLK.jpg"}, {"name": "\u6deb\u8361\u7559\u5b66\u751f\u300eMaominvshen\u300f\u4e0e\u5916\u56fd\u7537\u53cb\u7684\u6fc0\u60c5\u6027\u7231\u751f\u6d3b\u7cfb\u5217-\u5927\u767d\u5929\u5728\u6237\u5916\u638f\u51fa\u9e21\u5df4\u5c31\u5403 \u56de\u5230\u5bb6\u5c31\u9a91\u4e0a\u6765\u64cd\u903c", "size": 75579840, "link": "https://streamtape.com/e/9Ogo9eYOMRiYWJ", "created_at": "2022\u5e7404\u670830\u65e5 03:11:41", "downloads": 0, "linkid": "9Ogo9eYOMRiYWJ", "convert": "converted", "achorname": "\u4e38\u5b50\u5466", "subscribe": "0\u4f4d\u8ba2\u9605\u8005", "avatar-img": "https://huyaimg.msstatic.com/avatar/1022/07/ec5fef7c7662720286fbbb12395390_180_135.jpg?1628178596?458691", "folderName": "\u6deb\u8361\u7559\u5b66\u751f\u300eMaominvshen\u300f\u4e0e\u5916\u56fd\u7537\u53cb\u7684\u6fc0\u60c5\u6027\u7231\u751f\u6d3b\u7cfb\u5217-\u5927\u767d\u5929\u5728\u6237\u5916\u638f\u51fa\u9e21\u5df4\u5c31\u5403 \u56de\u5230\u5bb6\u5c31\u9a91\u4e0a\u6765\u64cd\u903c", "thumbUrl": "https://thumb.tapecontent.net/thumb/9Ogo9eYOMRiYWJ/RA73zrjdRXfdvWr.jpg"}, {"name": "\u5185\u5c04\u82d7\u6761\u7f8e\u5976\u5b66\u59b9", "size": 257538771, "link": "https://streamtape.com/e/GQKJbjejXxhd0B", "created_at": "2022\u5e7404\u670822\u65e5 09:52:27", "downloads": 0, "linkid": "GQKJbjejXxhd0B", "convert": "converted", "achorname": "\u4e38\u5b50\u5466", "subscribe": "0\u4f4d\u8ba2\u9605\u8005", "avatar-img": "https://huyaimg.msstatic.com/avatar/1022/07/ec5fef7c7662720286fbbb12395390_180_135.jpg?1628178596?458648", "folderName": "\u5185\u5c04\u82d7\u6761\u7f8e\u5976\u5b66\u59b9", "thumbUrl": "https://thumb.tapecontent.net/thumb/GQKJbjejXxhd0B/0VZR24AmBOSbXWR.jpg"}, {"name": "\u3010\u8d85\u63a8\u8350 \u4f1a\u5c0a\u4eab\u3011\u6d1b\u6749\u77f6\u534e\u4eba\u7559\u5b66\u751f\u300e\u8309\u8389\u300f\u9ad8\u989c\u503c\u60c5\u4fa3\u6027\u7231\u79c1\u62cd\u6d41\u51fa \u6d77\u8fb9\u522b\u5885\u6deb\u8361\u4e71\u64cd\u556a\u65e0\u5957\u5185\u5c04", "size": 48007697, "link": "https://streamtape.com/e/m1xer21KePIbma4", "created_at": "2022\u5e7405\u670804\u65e5 08:44:20", "downloads": 0, "linkid": "m1xer21KePIbma4", "convert": "converted", "achorname": "\u4e38\u5b50\u5466", "subscribe": "0\u4f4d\u8ba2\u9605\u8005", "avatar-img": "https://huyaimg.msstatic.com/avatar/1022/07/ec5fef7c7662720286fbbb12395390_180_135.jpg?1628178596?458792", "folderName": "\u3010\u8d85\u63a8\u8350 \u4f1a\u5c0a\u4eab\u3011\u6d1b\u6749\u77f6\u534e\u4eba\u7559\u5b66\u751f\u300e\u8309\u8389\u300f\u9ad8\u989c\u503c\u60c5\u4fa3\u6027\u7231\u79c1\u62cd\u6d41\u51fa \u6d77\u8fb9\u522b\u5885\u6deb\u8361\u4e71\u64cd\u556a\u65e0\u5957\u5185\u5c04", "thumbUrl": "https://thumb.tapecontent.net/thumb/m1xer21KePIbma4/pamPBwZ2dxfroBD.jpg"}, {"name": "\u6deb\u8361\u7559\u5b66\u751f\u300e\u732b\u54aa\u5973\u795e\u300f\u4e0e\u5916\u56fd\u7537\u53cb\u7684\u6fc0\u60c5\u6027\u7231\u751f\u6d3b\u7cfb\u5217-\u96be\u5fd8\u7684\u65b0\u5e74\u665a\u9910", "size": 59157007, "link": "https://streamtape.com/e/Lyj0MYyPvycRGpq", "created_at": "2022\u5e7405\u670801\u65e5 06:45:53", "downloads": 0, "linkid": "Lyj0MYyPvycRGpq", "convert": "converted", "achorname": "\u4e38\u5b50\u5466", "subscribe": "0\u4f4d\u8ba2\u9605\u8005", "avatar-img": "https://huyaimg.msstatic.com/avatar/1022/07/ec5fef7c7662720286fbbb12395390_180_135.jpg?1628178596?458718", "folderName": "\u6deb\u8361\u7559\u5b66\u751f\u300e\u732b\u54aa\u5973\u795e\u300f\u4e0e\u5916\u56fd\u7537\u53cb\u7684\u6fc0\u60c5\u6027\u7231\u751f\u6d3b\u7cfb\u5217-\u96be\u5fd8\u7684\u65b0\u5e74\u665a\u9910", "thumbUrl": "https://thumb.tapecontent.net/thumb/Lyj0MYyPvycRGpq/wYvodBaKy1fJMPZ.jpg"}, {"name": "\u6deb\u8361\u7559\u5b66\u751f\u300eMaominvshen\u300f\u4e0e\u5916\u56fd\u7537\u53cb\u7684\u6fc0\u60c5\u6027\u7231\u751f\u6d3b\u7cfb\u5217-\u5267\u60c5\u6f14\u7ece \u6a21\u7279\u52fe\u5f15\u6444\u5f71\u5e08\u6fc0\u60c5\u64cd\u903c", "size": 77090691, "link": "https://streamtape.com/e/YK1Vxp660VFvADg", "created_at": "2022\u5e7404\u670830\u65e5 06:06:33", "downloads": 0, "linkid": "YK1Vxp660VFvADg", "convert": "converted", "achorname": "\u4e38\u5b50\u5466", "subscribe": "0\u4f4d\u8ba2\u9605\u8005", "avatar-img": "https://huyaimg.msstatic.com/avatar/1022/07/ec5fef7c7662720286fbbb12395390_180_135.jpg?1628178596?458694", "folderName": "\u6deb\u8361\u7559\u5b66\u751f\u300eMaominvshen\u300f\u4e0e\u5916\u56fd\u7537\u53cb\u7684\u6fc0\u60c5\u6027\u7231\u751f\u6d3b\u7cfb\u5217-\u5267\u60c5\u6f14\u7ece \u6a21\u7279\u52fe\u5f15\u6444\u5f71\u5e08\u6fc0\u60c5\u64cd\u903c", "thumbUrl": "https://thumb.tapecontent.net/thumb/YK1Vxp660VFvADg/KZk6BJ29vxi0eBM.jpg"}, {"name": "\u3010\u5c0f\u8001\u864e\u63a2\u82b1\u3011\u731b\u864e\u4e0b\u5c71\uff0c\u5927\u6218\u767d\u5ae9\u7f8e\u4eba\u59bb\uff0c\u8fd9\u5927\u767d\u81c0\u592a\u7ed9\u529b\uff0c\u76f4\u547c\u53d7\u4e0d\u4e86\u7537\u4e3b\u7684\u5927\u9e21\u5df4\uff0c\u53eb\u58f0\u597d\u9a9a", "size": 77660796, "link": "https://streamtape.com/e/O2x3aAxkyoHZVX2", "created_at": "2022\u5e7404\u670823\u65e5 19:59:53", "downloads": 0, "linkid": "O2x3aAxkyoHZVX2", "convert": "converted", "achorname": "\u4e38\u5b50\u5466", "subscribe": "0\u4f4d\u8ba2\u9605\u8005", "avatar-img": "https://huyaimg.msstatic.com/avatar/1022/07/ec5fef7c7662720286fbbb12395390_180_135.jpg?1628178596?458648", "folderName": "\u3010\u5c0f\u8001\u864e\u63a2\u82b1\u3011\u731b\u864e\u4e0b\u5c71\uff0c\u5927\u6218\u767d\u5ae9\u7f8e\u4eba\u59bb\uff0c\u8fd9\u5927\u767d\u81c0\u592a\u7ed9\u529b\uff0c\u76f4\u547c\u53d7\u4e0d\u4e86\u7537\u4e3b\u7684\u5927\u9e21\u5df4\uff0c\u53eb\u58f0\u597d\u9a9a", "thumbUrl": "https://thumb.tapecontent.net/thumb/O2x3aAxkyoHZVX2/3pqWXKLjM3sd7XJ.jpg"}, {"name": "\u59d0\u59b9\u5973\u7f51\u7ea2\u9080\u8bf7\u516c\u4f1a\u5e05\u54e5\u73a94P\u5927\u6218", "size": 745129234, "link": "https://streamtape.com/e/KZd0xV9vwrSwBd", "created_at": "2022\u5e7404\u670823\u65e5 02:40:36", "downloads": 0, "linkid": "KZd0xV9vwrSwBd", "convert": "converted", "achorname": "\u4e38\u5b50\u5466", "subscribe": "0\u4f4d\u8ba2\u9605\u8005", "avatar-img": "https://huyaimg.msstatic.com/avatar/1022/07/ec5fef7c7662720286fbbb12395390_180_135.jpg?1628178596?458648", "folderName": "\u59d0\u59b9\u5973\u7f51\u7ea2\u9080\u8bf7\u516c\u4f1a\u5e05\u54e5\u73a94P\u5927\u6218", "thumbUrl": "https://thumb.tapecontent.net/thumb/KZd0xV9vwrSwBd/okboZvXqY2Tvvv.jpg"}, {"name": "\u82d7\u6761\u9a9a\u5973\u53cb\u559c\u6b22\u88ab\u540e\u5165", "size": 46590742, "link": "https://streamtape.com/e/26gYmLloz9TZ8BP", "created_at": "2022\u5e7404\u670810\u65e5 07:01:32", "downloads": 0, "linkid": "26gYmLloz9TZ8BP", "convert": "converted", "achorname": "\u4e38\u5b50\u5466", "subscribe": "0\u4f4d\u8ba2\u9605\u8005", "avatar-img": "https://huyaimg.msstatic.com/avatar/1022/07/ec5fef7c7662720286fbbb12395390_180_135.jpg?1628178596?458648", "folderName": "\u82d7\u6761\u9a9a\u5973\u53cb\u559c\u6b22\u88ab\u540e\u5165", "thumbUrl": "https://thumb.tapecontent.net/thumb/26gYmLloz9TZ8BP/PG9Y0dQBrYs0ZxK.jpg"}, {"name": "\u9a9a\u6c14\u58a8\u955c\u5c11\u5987\u548c\u70ae\u53cb\u6237\u5916\u91ce\u5730\u5927\u6218\uff0c\u8131\u4e0b\u5185\u88e4\u8214\u903c\u53e3\u4ea4\u7fd8\u8d77\u5c41\u80a1\u540e\u5165", "size": 291199025, "link": "https://streamtape.com/e/DWzJ92VlYxHkZbA", "created_at": "2022\u5e7404\u670828\u65e5 16:08:45", "downloads": 0, "linkid": "DWzJ92VlYxHkZbA", "convert": "converted", "achorname": "\u4e38\u5b50\u5466", "subscribe": "130.2\u4e07\u4f4d\u8ba2\u9605\u8005", "avatar-img": "https://huyaimg.msstatic.com/avatar/1022/07/ec5fef7c7662720286fbbb12395390_180_135.jpg?1628178596?458656", "folderName": "\u9a9a\u6c14\u58a8\u955c\u5c11\u5987\u548c\u70ae\u53cb\u6237\u5916\u91ce\u5730\u5927\u6218\uff0c\u8131\u4e0b\u5185\u88e4\u8214\u903c\u53e3\u4ea4\u7fd8\u8d77\u5c41\u80a1\u540e\u5165", "thumbUrl": "https://thumb.tapecontent.net/thumb/DWzJ92VlYxHkZbA/MqD2rbkdmaCm70M.jpg"}, {"name": "\u4e24\u7537\u4e00\u5973\u82d7\u6761\u59b9\u5b503P\u591a\u79cd\u59ff\u52bf\u6fc0\u60c5\u5927\u6218\uff0c\u540e\u9762\u62b1\u7740\u5c41\u80a1\u9a91\u4e58\u62bd\u63d2\uff0c\u55ef\u55ef\u55ef\u597d\u75db\u8fb9\u64cd\u8fb9\u53e3\u4ea4\uff0c\u82b1\u6837\u59ff\u52bf\u64cd\u7684\u4e00\u76f4\u547b\u541f", "size": 178245250, "link": "https://streamtape.com/e/888VVgmyVQToQk9", "created_at": "2022\u5e7405\u670804\u65e5 17:47:07", "downloads": 0, "linkid": "888VVgmyVQToQk9", "convert": "converted", "achorname": "\u4e38\u5b50\u5466", "subscribe": "0\u4f4d\u8ba2\u9605\u8005", "avatar-img": "https://huyaimg.msstatic.com/avatar/1022/07/ec5fef7c7662720286fbbb12395390_180_135.jpg?1628178596?458802", "folderName": "\u4e24\u7537\u4e00\u5973\u82d7\u6761\u59b9\u5b503P\u591a\u79cd\u59ff\u52bf\u6fc0\u60c5\u5927\u6218\uff0c\u540e\u9762\u62b1\u7740\u5c41\u80a1\u9a91\u4e58\u62bd\u63d2\uff0c\u55ef\u55ef\u55ef\u597d\u75db\u8fb9\u64cd\u8fb9\u53e3\u4ea4\uff0c\u82b1\u6837\u59ff\u52bf\u64cd\u7684\u4e00\u76f4\u547b\u541f", "thumbUrl": "https://thumb.tapecontent.net/thumb/888VVgmyVQToQk9/KyX1VXG9Zpc0XPP.jpg"}, {"name": "\u4e03\u5929\u9ad8\u7aef\u5916\u56f410-22\u5e74\u8f7b\u5c0f\u6a21", "size": 350719720, "link": "https://streamtape.com/e/3Vk877AO7AtdZrD", "created_at": "2022\u5e7403\u670814\u65e5 09:23:57", "downloads": 0, "linkid": "3Vk877AO7AtdZrD", "convert": "converted", "achorname": "\u4e38\u5b50\u5466", "subscribe": "0\u4f4d\u8ba2\u9605\u8005", "avatar-img": "https://huyaimg.msstatic.com/avatar/1022/07/ec5fef7c7662720286fbbb12395390_180_135.jpg?1628178596?458648", "folderName": "\u4e03\u5929\u9ad8\u7aef\u5916\u56f410-22\u5e74\u8f7b\u5c0f\u6a21", "thumbUrl": "https://thumb.tapecontent.net/thumb/3Vk877AO7AtdZrD/4mdDMQb9vluK01j.jpg"}, {"name": "\u6deb\u8361\u7559\u5b66\u751f\u4e0e\u6cd5\u56fd\u7537\u53cb\u73af\u7403\u65c5\u884c \u4e00\u8def\u73a9\u4e00\u8def\u64cd \u5929\u5929\u88ab\u64cd\u51fa\u767d\u6d46 \u9ad8\u6f6e\u4e0d\u65ad", "size": 44856775, "link": "https://streamtape.com/e/R7mW2YoJqXHdPJ0", "created_at": "2022\u5e7405\u670801\u65e5 15:06:22", "downloads": 0, "linkid": "R7mW2YoJqXHdPJ0", "convert": "converted", "achorname": "\u4e38\u5b50\u5466", "subscribe": "130.3\u4e07\u4f4d\u8ba2\u9605\u8005", "avatar-img": "https://huyaimg.msstatic.com/avatar/1022/07/ec5fef7c7662720286fbbb12395390_180_135.jpg?1628178596?458727", "folderName": "\u6deb\u8361\u7559\u5b66\u751f\u4e0e\u6cd5\u56fd\u7537\u53cb\u73af\u7403\u65c5\u884c \u4e00\u8def\u73a9\u4e00\u8def\u64cd \u5929\u5929\u88ab\u64cd\u51fa\u767d\u6d46 \u9ad8\u6f6e\u4e0d\u65ad", "thumbUrl": "https://thumb.tapecontent.net/thumb/R7mW2YoJqXHdPJ0/ZrelRGGXZxTqLey.jpg"}, {"name": "\u72fc\u54e5\u96c7\u4f63\u9ed1\u4eba\u7559\u5b66\u751f\u5bbe\u9986\u5ad6\u5993\u5077\u62cd\u300a\u9ed1\u4eba\u4f1a\u6240\u839e\u5f0f\u5927\u7535\u5f71\u300b\u5927\u5976\u5c11\u5987\u5973\u6280\u5e08\u4e00\u6761\u9f99\u556a\u556a", "size": 182669606, "link": "https://streamtape.com/e/zVb0av4m0OsYdZp", "created_at": "2022\u5e7404\u670825\u65e5 16:03:00", "downloads": 0, "linkid": "zVb0av4m0OsYdZp", "convert": "converted", "achorname": "\u4e38\u5b50\u5466", "subscribe": "0\u4f4d\u8ba2\u9605\u8005", "avatar-img": "https://huyaimg.msstatic.com/avatar/1022/07/ec5fef7c7662720286fbbb12395390_180_135.jpg?1628178596?458648", "folderName": "\u72fc\u54e5\u96c7\u4f63\u9ed1\u4eba\u7559\u5b66\u751f\u5bbe\u9986\u5ad6\u5993\u5077\u62cd\u300a\u9ed1\u4eba\u4f1a\u6240\u839e\u5f0f\u5927\u7535\u5f71\u300b\u5927\u5976\u5c11\u5987\u5973\u6280\u5e08\u4e00\u6761\u9f99\u556a\u556a", "thumbUrl": "https://thumb.tapecontent.net/thumb/zVb0av4m0OsYdZp/BPB3OgBg1vIyaOw.jpg"}, {"name": "\u5916\u8868\u65af\u6587\u773c\u955c\u7559\u5b66\u751f\u5047\u671f\u4e0d\u56de\u56fd\u5bbe\u9986\u73a9\u64cd\u6f02\u4eae\u5ae9\u6a21\u53c8\u62a0\u53c8\u8214\u6027\u7231\u59ff\u52bf\u73a9\u7684\u591a\u8001\u53f8\u673a\u4e00\u679a", "size": 54497709, "link": "https://streamtape.com/e/lOLRa1GPBPH7MaQ", "created_at": "2022\u5e7405\u670801\u65e5 08:43:53", "downloads": 0, "linkid": "lOLRa1GPBPH7MaQ", "convert": "converted", "achorname": "\u4e38\u5b50\u5466", "subscribe": "0\u4f4d\u8ba2\u9605\u8005", "avatar-img": "https://huyaimg.msstatic.com/avatar/1022/07/ec5fef7c7662720286fbbb12395390_180_135.jpg?1628178596?458720", "folderName": "\u5916\u8868\u65af\u6587\u773c\u955c\u7559\u5b66\u751f\u5047\u671f\u4e0d\u56de\u56fd\u5bbe\u9986\u73a9\u64cd\u6f02\u4eae\u5ae9\u6a21\u53c8\u62a0\u53c8\u8214\u6027\u7231\u59ff\u52bf\u73a9\u7684\u591a\u8001\u53f8\u673a\u4e00\u679a", "thumbUrl": "https://thumb.tapecontent.net/thumb/lOLRa1GPBPH7MaQ/oLXD1BMBJWHJ27V.jpg"}, {"name": "\u3010\u4eca\u65e5\u63a8\u8350\u3011\u56fd\u4ea7\u9a9a\u8d27\u7559\u5b66\u751f\u300e\u4e0b\u9762\u6709\u8ddf\u68d2\u68d2\u7cd6\u300f02.05\u6700\u65b0\u529b\u4f5c-\u8db3\u4ea4\u7206\u64cd\u5c04\u5728\u7ea6\u62cd\u767d\u864e\u6a21\u7279\u7684\u9ed1\u4e1d\u88e4\u889c\u4e0a", "size": 24850735, "link": "https://streamtape.com/e/vlxG0DyrxpT4g6P", "created_at": "2022\u5e7405\u670802\u65e5 10:44:27", "downloads": 0, "linkid": "vlxG0DyrxpT4g6P", "convert": "converted", "achorname": "\u4e38\u5b50\u5466", "subscribe": "0\u4f4d\u8ba2\u9605\u8005", "avatar-img": "https://huyaimg.msstatic.com/avatar/1022/07/ec5fef7c7662720286fbbb12395390_180_135.jpg?1628178596?458746", "folderName": "\u3010\u4eca\u65e5\u63a8\u8350\u3011\u56fd\u4ea7\u9a9a\u8d27\u7559\u5b66\u751f\u300e\u4e0b\u9762\u6709\u8ddf\u68d2\u68d2\u7cd6\u300f02.05\u6700\u65b0\u529b\u4f5c-\u8db3\u4ea4\u7206\u64cd\u5c04\u5728\u7ea6\u62cd\u767d\u864e\u6a21\u7279\u7684\u9ed1\u4e1d\u88e4\u889c\u4e0a", "thumbUrl": "https://thumb.tapecontent.net/thumb/vlxG0DyrxpT4g6P/7zmkP03pbkTAelM.jpg"}, {"name": "\u72fc\u54e5\u96c7\u4f63\u9ed1\u4eba\u7559\u5b66\u751f\u9152\u5e97\u5ad6\u5993\u5077\u62cd\u4e4b\u839e\u5f0f\u4f1a\u6240\u5927\u7535\u5f71\u4e0d\u65ad\u8981\u6c42\u52a0\u94b1\u7684\u5973\u6280\u5e08\u8bf4\u6c57\u592a\u591a\u6ca1\u5c04\u5c31\u4e0d\u8ba9\u5e72\u4e86", "size": 118440517, "link": "https://streamtape.com/e/Ky1dgpogk1cAve", "created_at": "2022\u5e7404\u670823\u65e5 06:30:17", "downloads": 0, "linkid": "Ky1dgpogk1cAve", "convert": "converted", "achorname": "\u4e38\u5b50\u5466", "subscribe": "0\u4f4d\u8ba2\u9605\u8005", "avatar-img": "https://huyaimg.msstatic.com/avatar/1022/07/ec5fef7c7662720286fbbb12395390_180_135.jpg?1628178596?458648", "folderName": "\u72fc\u54e5\u96c7\u4f63\u9ed1\u4eba\u7559\u5b66\u751f\u9152\u5e97\u5ad6\u5993\u5077\u62cd\u4e4b\u839e\u5f0f\u4f1a\u6240\u5927\u7535\u5f71\u4e0d\u65ad\u8981\u6c42\u52a0\u94b1\u7684\u5973\u6280\u5e08\u8bf4\u6c57\u592a\u591a\u6ca1\u5c04\u5c31\u4e0d\u8ba9\u5e72\u4e86", "thumbUrl": "https://thumb.tapecontent.net/thumb/Ky1dgpogk1cAve/yrKVKQOjLJU1QZd.jpg"}, {"name": "\u8272\u64ad\u98ce\u9a9a\u59b9\u5b50\u548c\u7537\u53cb\u5404\u4e2a\u59ff\u52bf\u5927\u6218", "size": 685613891, "link": "https://streamtape.com/e/1pmK7jRvqbseKWV", "created_at": "2022\u5e7404\u670822\u65e5 09:30:15", "downloads": 0, "linkid": "1pmK7jRvqbseKWV", "convert": "converted", "achorname": "\u4e38\u5b50\u5466", "subscribe": "0\u4f4d\u8ba2\u9605\u8005", "avatar-img": "https://huyaimg.msstatic.com/avatar/1022/07/ec5fef7c7662720286fbbb12395390_180_135.jpg?1628178596?458648", "folderName": "\u8272\u64ad\u98ce\u9a9a\u59b9\u5b50\u548c\u7537\u53cb\u5404\u4e2a\u59ff\u52bf\u5927\u6218", "thumbUrl": "https://thumb.tapecontent.net/thumb/1pmK7jRvqbseKWV/kpeZMoglldI9wA.jpg"}, {"name": "\u540e\u5165\u82d7\u6761\u6781\u54c1\u7f8e\u817f\u5973\u53cb", "size": 4268563614, "link": "https://streamtape.com/e/9pMxmL2gWWha3b3", "created_at": "2022\u5e7404\u670822\u65e5 18:04:16", "downloads": 0, "linkid": "9pMxmL2gWWha3b3", "convert": "converted", "achorname": "\u4e38\u5b50\u5466", "subscribe": "0\u4f4d\u8ba2\u9605\u8005", "avatar-img": "https://huyaimg.msstatic.com/avatar/1022/07/ec5fef7c7662720286fbbb12395390_180_135.jpg?1628178596?458648", "folderName": "\u540e\u5165\u82d7\u6761\u6781\u54c1\u7f8e\u817f\u5973\u53cb", "thumbUrl": "https://thumb.tapecontent.net/thumb/9pMxmL2gWWha3b3/BerZXjrr9btyB8v.jpg"}]